{
  "schema_version": "v1",
  "calibration": {
    "ms_per_episode_condition": 8000,
    "hardware": "Apple M2 Air 8 GB",
    "calibrated_at": "2026-03-16",
    "calibration_note": "With hazard_harm=0.02, avg episode ~182 steps (was ~18 with 0.5). Actual episode time higher."
  },
  "items": [
    {
      "queue_id": "V3-ONBOARD-smoke-EWINPC",
      "title": "Onboarding smoke test -- EWINPC (Eoin)",
      "experiment_type": "v3_onboard_smoke_EWINPC",
      "script": "experiments/v3_onboard_smoke_EWINPC.py",
      "machine_affinity": "EWINPC",
      "priority": 0,
      "status": "pending",
      "estimated_minutes": 20
    },
    {
      "queue_id": "V3-EXQ-074c",
      "title": "MECH-112/117 wanting/liking dissociation (detach fix)",
      "experiment_type": "v3_exq_074c_mech112_117_wanting_liking",
      "script": "experiments/v3_exq_074c_mech112_117_wanting_liking.py",
      "supersedes": "V3-EXQ-074b",
      "machine_affinity": "any",
      "priority": 2,
      "status": "pending",
      "estimated_minutes": 15,
      "seeds": 1,
      "conditions": 3,
      "args": [
        "--seed",
        "42",
        "--alpha-world",
        "0.9"
      ]
    },
    {
      "queue_id": "V3-EXQ-076c",
      "title": "MECH-116/ARC-032 E1 goal conditioning (frontal working memory, detach fix)",
      "experiment_type": "v3_exq_076c_mech116_arc032_e1_goal_conditioning",
      "script": "experiments/v3_exq_076c_mech116_arc032_e1_goal_conditioning.py",
      "supersedes": "V3-EXQ-076b",
      "machine_affinity": "any",
      "priority": 2,
      "status": "pending",
      "estimated_minutes": 10,
      "seeds": 1,
      "conditions": 2,
      "args": [
        "--seed",
        "42",
        "--alpha-world",
        "0.9"
      ]
    }
    ,
    {
      "queue_id": "V3-EXQ-099a",
      "title": "MECH-098 reafference upgrade gate + discriminative pair (collection filter fix)",
      "script": "experiments/v3_exq_099a_mech098_reafference_upgrade.py",
      "claim_id": "MECH-098",
      "supersedes": "V3-EXQ-099",
      "machine_affinity": "any",
      "priority": 2,
      "status": "pending",
      "estimated_minutes": 35,
      "args": "--alpha-world 0.9",
      "note": "Fixes EXQ-099 bug: collection filter was ttype=='none' but CausalGridWorldV2 reclassifies proximity steps to hazard_approach/benefit_approach, leaving ~8 samples. Fix: collect all non-genuine-world-event steps."
    }
  ]
}
